auditnlg/explain.py
auditnlg/llm_wrapper.py
auditnlg/utils.py
auditnlg/constraint/__init__.py
auditnlg/constraint/constraint_checker.py
auditnlg/constraint/exam.py
auditnlg/constraint/prompts.py
auditnlg/factualness/classifier.py
auditnlg/factualness/exam.py
auditnlg/factualness/utils.py
auditnlg/factualness/openAIscorers/constants.py
auditnlg/factualness/qafacteval_utils/answer_selection.py
auditnlg/factualness/qafacteval_utils/evaluator.py
auditnlg/factualness/qafacteval_utils/overall_model.py
auditnlg/factualness/qafacteval_utils/qa_model.py
auditnlg/factualness/qafacteval_utils/utils.py
auditnlg/factualness/summac_utils/evaluator.py
auditnlg/factualness/summac_utils/summac/setup.py
auditnlg/factualness/summac_utils/summac/summac/__init__.py
auditnlg/factualness/summac_utils/summac/summac/benchmark.py
auditnlg/factualness/summac_utils/summac/summac/model_baseline.py
auditnlg/factualness/summac_utils/summac/summac/model_guardrails.py
auditnlg/factualness/summac_utils/summac/summac/model_summac.py
auditnlg/factualness/summac_utils/summac/summac/run_baseline.py
auditnlg/factualness/summac_utils/summac/summac/train_summac.py
auditnlg/factualness/summac_utils/summac/summac/utils_misc.py
auditnlg/factualness/summac_utils/summac/summac/utils_optim.py
auditnlg/factualness/summac_utils/summac/summac/utils_scorer.py
auditnlg/factualness/summac_utils/summac/summac/utils_scoring.py
auditnlg/factualness/unieval_utils/evaluator.py
auditnlg/factualness/unieval_utils/scorer.py
auditnlg/regeneration/modeling.py
auditnlg/regeneration/prompt_helper.py
auditnlg/regeneration/constitutional_ai/__init__.py
auditnlg/regeneration/constitutional_ai/constants.py
auditnlg/regeneration/constitutional_ai/critique_revise.py
auditnlg/regeneration/prompt_expansion/__init__.py
auditnlg/regeneration/prompt_expansion/constants.py
auditnlg/regeneration/prompt_expansion/prompt_with_guidelines.py
auditnlg/regeneration/self_refine/__init__.py
auditnlg/regeneration/self_refine/constants.py
auditnlg-0.0.1.dist-info/LICENSE.txt
auditnlg-0.0.1.dist-info/METADATA
auditnlg-0.0.1.dist-info/WHEEL
auditnlg-0.0.1.dist-info/top_level.txt
auditnlg-0.0.1.dist-info/RECORD
