Metadata-Version: 2.1
Name: auditnlg
Version: 0.0.1
Summary: Auditing Generative AI Lanugage Modeling for Trustworthiness
Author-email: Jason Wu <wu.jason@salesforce.com>, Lidiya Murakhovs'ka <l.murakhovska@salesforce.com>, Prafulla Kumar Choubey <pchoubey@salesforce.com>, Alex Fabbri <afabbri@salesforce.com>, Divyansh Agarwal <divyansh.agarwal@salesforce.com>, Congying Xia <c.xia@salesforce.com>, Tian Xie <txie@salesforce.com>
Project-URL: Homepage, https://github.com/salesforce/AuditNLG
Classifier: Programming Language :: Python :: 3
Classifier: License :: OSI Approved :: BSD License
Classifier: Operating System :: OS Independent
Requires-Python: >=3.7
License-File: LICENSE.txt
Requires-Dist: huggingface-hub (>=0.14.1)
Requires-Dist: transformers
Requires-Dist: openai
Requires-Dist: google-api-python-client (>=1.12.8)
Requires-Dist: torch
Requires-Dist: detoxify
Requires-Dist: sentencepiece
Requires-Dist: langchain
Requires-Dist: nltk
Requires-Dist: parlai
Requires-Dist: rank-bm25
Requires-Dist: gdown
Requires-Dist: edlib
Requires-Dist: spacy
Requires-Dist: accelerate
